<?xml version="1.0" encoding="utf-8"?>
<TutorialSlides>
  <Slide>
    <Left name="Tutorial/Slide1_Spritesheet(left).png" frameWidth="620" frameHeight="610"/>
    <Right name="Tutorial/Slide1_Spritesheet(right).png" frameWidth="620" frameHeight="610"/>
    <Default name="Tutorial/Slide_1.png" frameWidth="120" frameHeight="120"/>
    <Animation name="Slide1.xml"/>
  </Slide>
  
  <Slide>
    <Left name="Tutorial/Slide2_Spritesheet(left).png" frameWidth="620" frameHeight="610"/>
    <Right name="Tutorial/Slide2_Spritesheet(right).png" frameWidth="620" frameHeight="610"/>
    <Default name="Tutorial/Slide_2.png" frameWidth="120" frameHeight="120"/>
    <Animation name="Slide2.xml"/>
  </Slide>
  
  <Slide>
    <Left name="Tutorial/Slide3_Spritesheet(left).png" frameWidth="620" frameHeight="610"/>
    <Right name="Tutorial/Slide3_Spritesheet(right).png" frameWidth="620" frameHeight="610"/>
    <Default name="Tutorial/Slide_3.png" frameWidth="120" frameHeight="120"/>
    <Animation name="Slide3.xml"/>
  </Slide>
  
  <Slide>
    <Left name="Tutorial/Slide4_Spritesheet(left).png" frameWidth="620" frameHeight="610"/>
    <Right name="Tutorial/Slide4_Spritesheet(right).png" frameWidth="620" frameHeight="610"/>
    <Default name="Tutorial/Slide_4.png" frameWidth="120" frameHeight="120"/>
    <Animation name="Slide4.xml"/>
  </Slide>
  
  <Slide>
    <Left name="Tutorial/Slide5_Spritesheet(left).png" frameWidth="620" frameHeight="610"/>
    <Right name="Tutorial/Slide5_Spritesheet(right).png" frameWidth="620" frameHeight="610"/>
    <Default name="Tutorial/Slide_5.png" frameWidth="120" frameHeight="120"/>
    <Animation name="Slide5.xml"/>
  </Slide>
  <Slide>
    <Left name="Tutorial/Slide6_Spritesheet(left).png" frameWidth="620" frameHeight="610"/>
    <Right name="Tutorial/Slide6_Spritesheet(right).png" frameWidth="620" frameHeight="610"/>
    <Default name="Tutorial/Slide_6.png" frameWidth="120" frameHeight="120"/>
    <Animation name="Slide6.xml"/>
  </Slide>
</TutorialSlides>